project_settings.py
project_settings-1.2.0.dist-info/DESCRIPTION.rst
project_settings-1.2.0.dist-info/METADATA
project_settings-1.2.0.dist-info/RECORD
project_settings-1.2.0.dist-info/WHEEL
project_settings-1.2.0.dist-info/metadata.json
project_settings-1.2.0.dist-info/top_level.txt
